yellowbox_kraft/__init__.py
yellowbox_kraft/_version.py
yellowbox_kraft/kraft.py
yellowbox_kraft-0.1.1.dist-info/LICENSE
yellowbox_kraft-0.1.1.dist-info/METADATA
yellowbox_kraft-0.1.1.dist-info/WHEEL
yellowbox_kraft-0.1.1.dist-info/RECORD
